hifiberrydsp/__init__.py
hifiberrydsp/conftest.py
hifiberrydsp/datatools.py
hifiberrydsp/dsptoolkit.py
hifiberrydsp/genclocks.py
hifiberrydsp/alsa/__init__.py
hifiberrydsp/alsa/alsasync.py
hifiberrydsp/client/__init__.py
hifiberrydsp/client/sigmatcp.py
hifiberrydsp/filtering/__init__.py
hifiberrydsp/filtering/biquad.py
hifiberrydsp/filtering/filtermath.py
hifiberrydsp/filtering/volume.py
hifiberrydsp/filtering/volume_test.py
hifiberrydsp/hardware/__init__.py
hifiberrydsp/hardware/adau145x.py
hifiberrydsp/hardware/adau145x_test.py
hifiberrydsp/hardware/spi.py
hifiberrydsp/lg/__init__.py
hifiberrydsp/lg/soundsync.py
hifiberrydsp/lg/test_soundsync.py
hifiberrydsp/measurement/__init__.py
hifiberrydsp/measurement/data.py
hifiberrydsp/parser/__init__.py
hifiberrydsp/parser/biquad.py
hifiberrydsp/parser/rew.py
hifiberrydsp/parser/settings.py
hifiberrydsp/parser/sigmaparams.py
hifiberrydsp/parser/xmlprofile.py
hifiberrydsp/server/__init__.py
hifiberrydsp/server/constants.py
hifiberrydsp/server/sigmatcp.py
hifiberrydsp-0.21.data/scripts/dsptoolkit
hifiberrydsp-0.21.data/scripts/mergeparameters
hifiberrydsp-0.21.data/scripts/optimizer-client
hifiberrydsp-0.21.data/scripts/sigmatcpserver
hifiberrydsp-0.21.data/scripts/spdifclockgen
hifiberrydsp-0.21.dist-info/LICENSE
hifiberrydsp-0.21.dist-info/METADATA
hifiberrydsp-0.21.dist-info/WHEEL
hifiberrydsp-0.21.dist-info/top_level.txt
hifiberrydsp-0.21.dist-info/RECORD
